swtermcolor/__init__.py
swtermcolor/swtermcolor.py
swtermcolor/termcolor.py
SWTermColor-1.1.dist-info/LICENSE
SWTermColor-1.1.dist-info/METADATA
SWTermColor-1.1.dist-info/WHEEL
SWTermColor-1.1.dist-info/top_level.txt
SWTermColor-1.1.dist-info/RECORD
